[
  {
    "verse_number": 964.0,
    "line_number": 1.0,
    "chapter": "ನಗೆ_ಜೀವದುಲ್ಲಾಸ",
    "kannada_original": "ಹಾರಬಲ್ಲದೆ ಹಕ್ಕಿ ಹಾಯಾಗಿ ಅಂಬರದಿ",
    "english_transliteration": "Hārabaallade hakki hāyāagi aṁbaradi",
    "english_translation": "Can a bird fly comfortably in the sky",
    "tags": ""
  },
  {
    "verse_number": 964.0,
    "line_number": 2.0,
    "chapter": "ನಗೆ_ಜೀವದುಲ್ಲಾಸ",
    "kannada_original": "ಕಳೆದುಕೊಂಡರೆ ತನ್ನ ರೆಕ್ಕೆ ಸಾಮರ್ಥ್ಯ ?",
    "english_transliteration": "Kaḷedukoṇḍare tanna rekke sāamarthya ?",
    "english_translation": "If it loses the capability of its wings?",
    "tags": ""
  },
  {
    "verse_number": 964.0,
    "line_number": 3.0,
    "chapter": "ನಗೆ_ಜೀವದುಲ್ಲಾಸ",
    "kannada_original": "ಉಳಿಸಿಕೋ ನಿನ್ನತನ ; ಬಲ ಬಂದು ಅಡರುವುದು ;",
    "english_transliteration": "Uḷisikō ninnatana ; bala bandu aḍaruvudu ;",
    "english_translation": "Save your individuality; strength will come and spread;",
    "tags": ""
  },
  {
    "verse_number": 964.0,
    "line_number": 4.0,
    "chapter": "ನಗೆ_ಜೀವದುಲ್ಲಾಸ",
    "kannada_original": "ಹಾರು ನೀ ಸಾಹಸದಿ – ಮುದ್ದು ರಾಮ.",
    "english_transliteration": "Hāaru nī sāhasadi – Muddu Rāma.",
    "english_translation": "You fly with courage – Dear Rama.",
    "tags": ""
  }
]