[
  {
    "verse_number": 432.0,
    "line_number": 1.0,
    "chapter": "ಚೆಲುವು_ಪ್ರಕೃತಿಯ_ಕೊಡುಗೆ",
    "kannada_original": "ದಿವ್ಯ ಪೂರ್ಣಿಮೆ ಎನ್ನು : ಚಿತ್ರ ಹುಣ್ಣಿಮೆ ಎನ್ನು",
    "english_transliteration": "Divya pūrṇime ennu : chitra huṇṇime ennu",
    "english_translation": "Say divine full moon: say Chitra full moon;",
    "tags": ""
  },
  {
    "verse_number": 432.0,
    "line_number": 2.0,
    "chapter": "ಚೆಲುವು_ಪ್ರಕೃತಿಯ_ಕೊಡುಗೆ",
    "kannada_original": "ಇದೆ ಚೆಲುವು ಚೈತನ್ಯ ನೋಟಸುಖದಲ್ಲಿ.",
    "english_transliteration": "Ide cheluvu chaitanya nōṭasukhadalli.",
    "english_translation": "This beauty is consciousness in the pleasure of seeing.",
    "tags": ""
  },
  {
    "verse_number": 432.0,
    "line_number": 3.0,
    "chapter": "ಚೆಲುವು_ಪ್ರಕೃತಿಯ_ಕೊಡುಗೆ",
    "kannada_original": "ಹೆಸರಲೇನಿದೆ ಸೊಗಸು ? ಹಿರಿದು ಸತ್ವದ ಸೊಬಗು",
    "english_transliteration": "Hesarelēnide sogasu ? Hiridu satvada sobaga",
    "english_translation": "What beauty is there in the name? Greater is the charm of the essence;",
    "tags": ""
  },
  {
    "verse_number": 432.0,
    "line_number": 4.0,
    "chapter": "ಚೆಲುವು_ಪ್ರಕೃತಿಯ_ಕೊಡುಗೆ",
    "kannada_original": "ಚಿದ್ರೂಪ ಆನಂದ – ಮುದ್ದು ರಾಮ.",
    "english_transliteration": "Chidrūpa ānanda – Muddu Rāma.",
    "english_translation": "Consciousness-form is bliss – Dear Rāma.",
    "tags": ""
  }
]