[
  {
    "verse_number": 647.0,
    "line_number": 1.0,
    "chapter": "ಬಾಳು_ಆಶಾಬಿಂಬ",
    "kannada_original": "ತೋಡದಿರು ತಳಹದಿಯ ತಳಮಳದ ಮಂದಿರಕೆ",
    "english_transliteration": "Tōḍadiru taḷahadiya taḷamaḷada mandirake",
    "english_translation": "Do not dig the foundation for the temple of anxiety",
    "tags": ""
  },
  {
    "verse_number": 647.0,
    "line_number": 2.0,
    "chapter": "ಬಾಳು_ಆಶಾಬಿಂಬ",
    "kannada_original": "ಹೊಳಪಿಲ್ಲ ಗೋಪುರದಿ ಇಲ್ಲದಿರೆ ಶಾಂತಿ.",
    "english_transliteration": "Hoḷapilla gōpuradi illadire śānti.",
    "english_translation": "There is no luster in the tower if there is no peace.",
    "tags": ""
  },
  {
    "verse_number": 647.0,
    "line_number": 3.0,
    "chapter": "ಬಾಳು_ಆಶಾಬಿಂಬ",
    "kannada_original": "ಭಾವ ಬೆಸೆಯದೆ, ಬರಿದೆ ಶಿಲೆಯನಿಟ್ಟರೆ ಬಂತೆ?",
    "english_transliteration": "Bhāva beseyade, baride śileyaniṭṭare bante?",
    "english_translation": "If feelings are not intertwined, what is gained by merely placing stones?",
    "tags": ""
  },
  {
    "verse_number": 647.0,
    "line_number": 4.0,
    "chapter": "ಬಾಳು_ಆಶಾಬಿಂಬ",
    "kannada_original": "ಬದುಕು ಸಂತಸ ನೆಲೆಯೊ! – ಮುದ್ದು ರಾಮ.",
    "english_transliteration": "Baduku santasa neleyo! – Muddu Rāma.",
    "english_translation": "Is life a dwelling place of happiness? – Muddu Rama.",
    "tags": ""
  }
]