[
  {
    "verse_number": 906.0,
    "line_number": 1.0,
    "chapter": "ನಗೆ_ಜೀವದುಲ್ಲಾಸ",
    "kannada_original": "ಸೋತರೇನಿದೆ ಸೊಬಗು ದಿನದಿನದ ದುಡಿಮೆಯಲಿ ?",
    "english_transliteration": "Sōtarēnide sobagu dinadinada duḍiyemali ?",
    "english_translation": "What beauty is there in daily hard work if you lose?",
    "tags": ""
  },
  {
    "verse_number": 906.0,
    "line_number": 2.0,
    "chapter": "ನಗೆ_ಜೀವದುಲ್ಲಾಸ",
    "kannada_original": "ನಲಿದರಿದೆ ನಾವಿನ್ಯ, ಆಂತರ ಕಾಂತಿ.",
    "english_transliteration": "Naliidaride nāvinya, āantara kāanti.",
    "english_translation": "If you rejoice, there is innovation, inner radiance.",
    "tags": ""
  },
  {
    "verse_number": 906.0,
    "line_number": 3.0,
    "chapter": "ನಗೆ_ಜೀವದುಲ್ಲಾಸ",
    "kannada_original": "ಕಾರ್ಯ ಮರೆತರೆ ಸೋಲು, ಕನಸು ಸುಳಿದರೆ ಗೆಲುವು",
    "english_transliteration": "Kārya maretare sōlu, kanasu suḷidare geluvu",
    "english_translation": "Forgetting action is defeat, if a dream flows in, it is victory",
    "tags": ""
  },
  {
    "verse_number": 906.0,
    "line_number": 4.0,
    "chapter": "ನಗೆ_ಜೀವದುಲ್ಲಾಸ",
    "kannada_original": "ನಲಿವು ಗೆಲುವಿನ ಚಿಹ್ನೆ – ಮುದ್ದು ರಾಮ.",
    "english_transliteration": "Nalivu geluvina cihne – Muddu Rāma.",
    "english_translation": "Joy is the sign of victory – Dear Rama.",
    "tags": ""
  }
]