[
  {
    "verse_number": 84.0,
    "line_number": 1.0,
    "chapter": "ಸೃಷ್ಟಿ_ಕೌತುಕದೊಡಲು",
    "kannada_original": "ಜೇಡಿಮಣ್ಣಿನ ಗಡಿಗೆ ತಾಪದಿಂದತಿ ಗಡುಸು ;",
    "english_transliteration": "Jēḍimaṇṇina gaḍige tāpadindati gaḍusu;",
    "english_translation": "The clay pot becomes very hard due to heat;",
    "tags": ""
  },
  {
    "verse_number": 84.0,
    "line_number": 2.0,
    "chapter": "ಸೃಷ್ಟಿ_ಕೌತುಕದೊಡಲು",
    "kannada_original": "ಕರಗಿ ನಿಲುವುದು ಮೇಣ ಅದೆ ತಾಪದಿಂದ.",
    "english_transliteration": "Karagi niluvudu mēṇa ade tāpadinda.",
    "english_translation": "Wax melts and stops due to the same heat.",
    "tags": ""
  },
  {
    "verse_number": 84.0,
    "line_number": 3.0,
    "chapter": "ಸೃಷ್ಟಿ_ಕೌತುಕದೊಡಲು",
    "kannada_original": "ಒಂದ ಘನವಾಗಿಸುತ ದ್ರವವಾಗಿಸುವುದೊಂದ ;",
    "english_transliteration": "Onda ghanavāgisuta dravavāgisuvudondu;",
    "english_translation": "One thing is made solid, another is made liquid;",
    "tags": ""
  },
  {
    "verse_number": 84.0,
    "line_number": 4.0,
    "chapter": "ಸೃಷ್ಟಿ_ಕೌತುಕದೊಡಲು",
    "kannada_original": "ಎನಿತೊಂದು ವೈಚಿತ್ರ್ಯ ! – ಮುದ್ದು ರಾಮ.",
    "english_transliteration": "Enitondu vaicitrya! – Muddu Rāma.",
    "english_translation": "What a great variety/wonder! – Muddu Rāma.",
    "tags": ""
  }
]