[
  {
    "verse_number": 717.0,
    "line_number": 1.0,
    "chapter": "ಬಾಳು_ಆಶಾಬಿಂಬ",
    "kannada_original": "ಇರುಳು ಮುಗಿಯದ ಹೊರತು ಬೆಳಕು ಮನೆಮಾಡುವುದೆ?",
    "english_transliteration": "Iruḷu mugiyada horatu beḷaku manemāḍuvude?",
    "english_translation": "Will light settle until the night ends?",
    "tags": ""
  },
  {
    "verse_number": 717.0,
    "line_number": 2.0,
    "chapter": "ಬಾಳು_ಆಶಾಬಿಂಬ",
    "kannada_original": "ಬೆಳಕು ಸರಿ ಪಸರದಿರೆ ಮನಸು ಅರಳುವುದೆ?",
    "english_transliteration": "Beḷaku sari pasaradire manasu araḷuvude?",
    "english_translation": "If light does not spread properly, will the mind blossom?",
    "tags": ""
  },
  {
    "verse_number": 717.0,
    "line_number": 3.0,
    "chapter": "ಬಾಳು_ಆಶಾಬಿಂಬ",
    "kannada_original": "ಮನಸು ಹಸಿರಾಗದಿರೆ ಆ ಹಗಲೆ ಮುಸ್ಸಂಜೆ!",
    "english_transliteration": "Manasu hasirāgadire ā hagale mussanje!",
    "english_translation": "If the mind does not become green (fresh), that very day is dusk!",
    "tags": ""
  },
  {
    "verse_number": 717.0,
    "line_number": 4.0,
    "chapter": "ಬಾಳು_ಆಶಾಬಿಂಬ",
    "kannada_original": "ಸಂಜೆಯೆಂದರೆ ಇಳಿತ! - ಮುದ್ದು ರಾಮ.",
    "english_transliteration": "Sanjeyendare iḷita! - Muddu Rāma.",
    "english_translation": "Dusk means decline/descent! – Muddu Rama.",
    "tags": ""
  }
]