[
  {
    "verse_number": 379.0,
    "line_number": 1.0,
    "chapter": "ಮನಸೊಂದು_ಉದ್ಯಾನ",
    "kannada_original": "ದಿನದಿನದ ಅಬ್ಬರದ ಸದ್ದು ಗದ್ದಲದಲ್ಲಿ",
    "english_transliteration": "Dinadinada abbarada saddu gaddaladalli",
    "english_translation": "In the daily hustle, noise, and confusion.",
    "tags": ""
  },
  {
    "verse_number": 379.0,
    "line_number": 2.0,
    "chapter": "ಮನಸೊಂದು_ಉದ್ಯಾನ",
    "kannada_original": "ಅರಸು ನೀ ಏಕಾಂತ ಸ್ವಾತಂತ್ರ್ಯ ಸುಖವ.",
    "english_transliteration": "Arasu nī ēkānta svātantrya sukhava.",
    "english_translation": "You seek the happiness of solitude and freedom.",
    "tags": ""
  },
  {
    "verse_number": 379.0,
    "line_number": 3.0,
    "chapter": "ಮನಸೊಂದು_ಉದ್ಯಾನ",
    "kannada_original": "ಇದೆ ಆಗ ಮಾಧುರ, ಶ್ರೀಮಂತ ಗಾಂಭೀರ,",
    "english_transliteration": "Ide āga mādhura, śrīmanta gāmbhīra,",
    "english_translation": "That itself is then sweetness, rich profundity (gravity).",
    "tags": ""
  },
  {
    "verse_number": 379.0,
    "line_number": 4.0,
    "chapter": "ಮನಸೊಂದು_ಉದ್ಯಾನ",
    "kannada_original": "ಇರು ನೀನು ನಿನ್ನಂತೆ - ಮುದ್ದು ರಾಮ.",
    "english_transliteration": "Iru nīnu ninnante - Muddu Rāma.",
    "english_translation": "You be as you are – Muddu Rama.",
    "tags": ""
  }
]