[
  {
    "verse_number": 378.0,
    "line_number": 1.0,
    "chapter": "ಮನಸೊಂದು_ಉದ್ಯಾನ",
    "kannada_original": "ಮುದಕೆ ಕಾರಣವೆಂದು ಇಂದು ನೀ ತಿಳಿದದ್ದು",
    "english_transliteration": "Mudake kāraṇavendu indu nī tiḷidaddu",
    "english_translation": "What you considered today to be the cause of joy.",
    "tags": ""
  },
  {
    "verse_number": 378.0,
    "line_number": 2.0,
    "chapter": "ಮನಸೊಂದು_ಉದ್ಯಾನ",
    "kannada_original": "ಅದೆ ನಾಳೆ ತೊಂದರೆಗೆ ಮುಳುವಾಗಬಹುದು.",
    "english_transliteration": "Ade nāḷe tondarege muḷuvāgabahudu.",
    "english_translation": "That same thing may become the cause of trouble tomorrow.",
    "tags": ""
  },
  {
    "verse_number": 378.0,
    "line_number": 3.0,
    "chapter": "ಮನಸೊಂದು_ಉದ್ಯಾನ",
    "kannada_original": "ಸುಖದ ನೆಲೆ ಅದರ ಪರಿ ಯಕ್ಷಿಣಿಯ ಕಣ್ಣಟ್ಟು",
    "english_transliteration": "Sukhada nele adara pari yakṣiṇiya kaṇṇaṭṭu",
    "english_translation": "The abode of happiness and its nature is like the gaze of a Yakshini (illusion).",
    "tags": ""
  },
  {
    "verse_number": 378.0,
    "line_number": 4.0,
    "chapter": "ಮನಸೊಂದು_ಉದ್ಯಾನ",
    "kannada_original": "ಸಮಭಾವ ನೈಜಗುಣ – ಮುದ್ದು ರಾಮ.",
    "english_transliteration": "Samabhāva naijaguṇa – Muddu Rāma.",
    "english_translation": "Equanimity/balanced outlook is the true quality – Muddu Rama.",
    "tags": ""
  }
]