[
  {
    "verse_number": 488.0,
    "line_number": 1.0,
    "chapter": "ಕುಂದದಿರುವುದೆ_ಮೌಲ್ಯ",
    "kannada_original": "ತುಣಕೊಂದ ತಾ ತಿನದೆ ಕೊಟ್ಟರದು ಔದಾರ",
    "english_transliteration": "tuṇakoṃda tā tinade koṭṭaradu audāra",
    "english_translation": "Giving away a piece without eating it oneself is generosity,",
    "tags": ""
  },
  {
    "verse_number": 488.0,
    "line_number": 2.0,
    "chapter": "ಕುಂದದಿರುವುದೆ_ಮೌಲ್ಯ",
    "kannada_original": "ಬೇಕೆನುವ ಭಾವನೆಯೆ ಗಿಳಿಯ ಪಂಜರವೊ !",
    "english_transliteration": "bēkenuva bhāvaneye giḷiya paṃjaravo!",
    "english_translation": "The feeling of wanting is the cage of the parrot!",
    "tags": ""
  },
  {
    "verse_number": 488.0,
    "line_number": 3.0,
    "chapter": "ಕುಂದದಿರುವುದೆ_ಮೌಲ್ಯ",
    "kannada_original": "ಕೊಡುವ ಸುಂದರ ಮನಸು ಅನ್ನದಕ್ಷಯ ಪಾತ್ರೆ",
    "english_transliteration": "koḍuva suṃdara manasu annadakṣaya pātre",
    "english_translation": "A beautiful giving mind is an everlasting vessel of food",
    "tags": ""
  },
  {
    "verse_number": 488.0,
    "line_number": 4.0,
    "chapter": "ಕುಂದದಿರುವುದೆ_ಮೌಲ್ಯ",
    "kannada_original": "ಮನೆಗಿಂತ ಮನ ಹಿರಿದು ! – ಮುದ್ದು ರಾಮ. 488",
    "english_transliteration": "manegiṃta mana hiridu! – Muddu Rāma. 488",
    "english_translation": "The heart is greater than the house! – Muddu Rāma. 488",
    "tags": ""
  }
]