[
  {
    "verse_number": 477.0,
    "line_number": 1.0,
    "chapter": "ಕುಂದದಿರುವುದೆ_ಮೌಲ್ಯ",
    "kannada_original": "ಬಿದ್ದವರನೆತ್ತದಿರೆ ಜೀವಿತಕೆ ಬೆಲೆಯೇನು ?",
    "english_transliteration": "biddavaranettadire jīvitake beleyēnu?",
    "english_translation": "If you do not lift up the fallen, what is the value of life?",
    "tags": ""
  },
  {
    "verse_number": 477.0,
    "line_number": 2.0,
    "chapter": "ಕುಂದದಿರುವುದೆ_ಮೌಲ್ಯ",
    "kannada_original": "ಸಂತಾಪ ಪರಿಹಾರ ಮನುಜಗುಣ ಧರ್ಮ.",
    "english_transliteration": "santāpa parihāra manujaguṇa dharma.",
    "english_translation": "Removing sorrow is the dharma of human quality (humanity).",
    "tags": ""
  },
  {
    "verse_number": 477.0,
    "line_number": 3.0,
    "chapter": "ಕುಂದದಿರುವುದೆ_ಮೌಲ್ಯ",
    "kannada_original": "ಯಾರು ಅತಿ ತಗ್ಗುವರೊ, ಅವರು ಮೇಲೇರುವರು",
    "english_transliteration": "yāru ati tagguvaro, avaru mēlēruvaru",
    "english_translation": "Those who bend lowest are the ones who rise highest",
    "tags": ""
  },
  {
    "verse_number": 477.0,
    "line_number": 4.0,
    "chapter": "ಕುಂದದಿರುವುದೆ_ಮೌಲ್ಯ",
    "kannada_original": "ಅನುಕಂಪ ದಿವ್ಯತೆಯೊ ! – ಮುದ್ದು ರಾಮ. 477",
    "english_transliteration": "anukampa divyateyo! – Muddu Rāma. 477",
    "english_translation": "Is not compassion divinity! – Muddu Rāma. 477",
    "tags": ""
  }
]