[
  {
    "verse_number": 577.0,
    "line_number": 1.0,
    "chapter": "ಕುಂದದಿರುವುದೆ_ಮೌಲ್ಯ",
    "kannada_original": "ಕಳ್ಳತನ ಸುಳ್ಳುತನ ಹಿಂಸೆ ಮೊದಲಾದುದಕೆ",
    "english_transliteration": "kaḷḷatana suḷḷutana hiṃse modalādudake",
    "english_translation": "If you do not bow your head in shame for theft, lying, violence, and the like,",
    "tags": ""
  },
  {
    "verse_number": 577.0,
    "line_number": 2.0,
    "chapter": "ಕುಂದದಿರುವುದೆ_ಮೌಲ್ಯ",
    "kannada_original": "ನಾಚಿ ತಲೆ ತಗ್ಗದಿರೆ ಅದು ಮೌಲ್ಯಕುಸಿತ.",
    "english_transliteration": "nāci tale taggadire adu maulyakusita.",
    "english_translation": "that is a fall in values.",
    "tags": ""
  },
  {
    "verse_number": 577.0,
    "line_number": 3.0,
    "chapter": "ಕುಂದದಿರುವುದೆ_ಮೌಲ್ಯ",
    "kannada_original": "ತಪ್ಪೆಸಗಿ ಕರಕಟ್ಟಿ ನಿಂತರದು ಅವಮಾನ",
    "english_transliteration": "tappesagi karakaṭṭi nintaradu avamāna",
    "english_translation": "It is a disgrace to stand with bound hands after committing a mistake",
    "tags": ""
  },
  {
    "verse_number": 577.0,
    "line_number": 4.0,
    "chapter": "ಕುಂದದಿರುವುದೆ_ಮೌಲ್ಯ",
    "kannada_original": "ನಾಚುವುದೆ ಬಡತನಕೆ ? – ಮುದ್ದು ರಾಮ. 577",
    "english_transliteration": "nācuvude baḍatanake? – Muddu Rāma. 577",
    "english_translation": "Should one be ashamed of poverty? – Muddu Rāma. 577",
    "tags": ""
  }
]