[
  {
    "verse_number": 694.0,
    "line_number": 1.0,
    "chapter": "ಬಾಳು_ಆಶಾಬಿಂಬ",
    "kannada_original": "ನಿನ್ನದೋ ದೊರಕಿದುದು! ಸಿಗದದ್ದು ನಿನದಲ್ಲ.",
    "english_transliteration": "Ninnadō dorakidudu! Sigadaddu ninadalla.",
    "english_translation": "What you have obtained is yours! What you didn't get is not yours.",
    "tags": ""
  },
  {
    "verse_number": 694.0,
    "line_number": 2.0,
    "chapter": "ಬಾಳು_ಆಶಾಬಿಂಬ",
    "kannada_original": "ಬರದುದಕೆ ಬಾಯ್ದಿಟ್ಟು ಜೊಲ್ಲ ಸುರಿಸದಿರು.",
    "english_transliteration": "Baradudake bāyidiṭṭu jolla surisadiru.",
    "english_translation": "Do not open your mouth and drool for what has not come.",
    "tags": ""
  },
  {
    "verse_number": 694.0,
    "line_number": 3.0,
    "chapter": "ಬಾಳು_ಆಶಾಬಿಂಬ",
    "kannada_original": "ಇರದುದಕೆ ಶೋಕಿಸದೆ ನಲಿ ನೀನು ಇರುವುದಕೆ;",
    "english_transliteration": "Iradudake śōkisade nali nīnu iruvudake;",
    "english_translation": "Do not mourn for what is absent, rejoice for what is present;",
    "tags": ""
  },
  {
    "verse_number": 694.0,
    "line_number": 4.0,
    "chapter": "ಬಾಳು_ಆಶಾಬಿಂಬ",
    "kannada_original": "ಬದುಕು ಹಗರಣವಲ್ಲ – ಮುದ್ದು ರಾಮ.",
    "english_transliteration": "Baduku hagaraṇavalla – Muddu Rāma.",
    "english_translation": "Life is not a scandal/deception – Muddu Rama.",
    "tags": ""
  }
]