[
  {
    "verse_number": 481.0,
    "line_number": 1.0,
    "chapter": "ಕುಂದದಿರುವುದೆ_ಮೌಲ್ಯ",
    "kannada_original": "ಕ್ರಿಸ್ತಮುಸ್ಲಿ ಮಹಿಂದು ಸಿಪಾರಸಿಜೈನ",
    "english_transliteration": "kristamusli mahindu sipārasijaina",
    "english_translation": "Christian, Muslim, Hindu, Sikh, Parsi, Jain,",
    "tags": ""
  },
  {
    "verse_number": 481.0,
    "line_number": 2.0,
    "chapter": "ಕುಂದದಿರುವುದೆ_ಮೌಲ್ಯ",
    "kannada_original": "ಯಾರೆ ಇರು, ಆಗು, ಮೊದಲು ಮಾನವ ನೀನು.",
    "english_transliteration": "yāre iru, āgu, modalu mānava nīnu.",
    "english_translation": "Whoever you are, become, first, a human being.",
    "tags": ""
  },
  {
    "verse_number": 481.0,
    "line_number": 3.0,
    "chapter": "ಕುಂದದಿರುವುದೆ_ಮೌಲ್ಯ",
    "kannada_original": "ಕರುಣೆನದಿ ಹರಿದಿಲ್ಲಿ ಜೀವ ಹಸಿರಾದೀತು !",
    "english_transliteration": "karuṇenadi haridilli jīva hasirādītu!",
    "english_translation": "Let the river of mercy flow here so life can be green!",
    "tags": ""
  },
  {
    "verse_number": 481.0,
    "line_number": 4.0,
    "chapter": "ಕುಂದದಿರುವುದೆ_ಮೌಲ್ಯ",
    "kannada_original": "ಸಮರ ಕರುಣೆಗೆ ಸಮವೆ ?– ಮುದ್ದು ರಾಮ. 481",
    "english_transliteration": "samara karuṇege samave?– Muddu Rāma. 481",
    "english_translation": "Is war equal to mercy?– Muddu Rāma. 481",
    "tags": ""
  }
]